<annotation>
	<folder>train</folder>
	<filename>134.jpg</filename>
	<path>C:\Users\top\Desktop\project\uncaptcha_api\data\images\train\134.jpg</path>
	<source>
		<database>Unknown</database>
	</source>
	<size>
		<width>300</width>
		<height>300</height>
		<depth>3</depth>
	</size>
	<segmented>0</segmented>
	<object>
		<name>行人穿越道</name>
		<pose>Unspecified</pose>
		<truncated>0</truncated>
		<difficult>0</difficult>
		<bndbox>
			<xmin>45</xmin>
			<ymin>19</ymin>
			<xmax>99</xmax>
			<ymax>99</ymax>
		</bndbox>
	</object>
	<object>
		<name>行人穿越道</name>
		<pose>Unspecified</pose>
		<truncated>1</truncated>
		<difficult>0</difficult>
		<bndbox>
			<xmin>1</xmin>
			<ymin>130</ymin>
			<xmax>100</xmax>
			<ymax>194</ymax>
		</bndbox>
	</object>
	<object>
		<name>行人穿越道</name>
		<pose>Unspecified</pose>
		<truncated>1</truncated>
		<difficult>0</difficult>
		<bndbox>
			<xmin>259</xmin>
			<ymin>244</ymin>
			<xmax>300</xmax>
			<ymax>266</ymax>
		</bndbox>
	</object>
	<object>
		<name>汽車</name>
		<pose>Unspecified</pose>
		<truncated>0</truncated>
		<difficult>0</difficult>
		<bndbox>
			<xmin>122</xmin>
			<ymin>267</ymin>
			<xmax>164</xmax>
			<ymax>289</ymax>
		</bndbox>
	</object>
	<object>
		<name>汽車</name>
		<pose>Unspecified</pose>
		<truncated>0</truncated>
		<difficult>0</difficult>
		<bndbox>
			<xmin>156</xmin>
			<ymin>184</ymin>
			<xmax>199</xmax>
			<ymax>200</ymax>
		</bndbox>
	</object>
	<object>
		<name>棕梠樹</name>
		<pose>Unspecified</pose>
		<truncated>1</truncated>
		<difficult>0</difficult>
		<bndbox>
			<xmin>170</xmin>
			<ymin>1</ymin>
			<xmax>202</xmax>
			<ymax>91</ymax>
		</bndbox>
	</object>
</annotation>
