<annotation>
	<folder>train</folder>
	<filename>88.jpg</filename>
	<path>C:\Users\top\Desktop\project\uncaptcha_api\data\images\train\88.jpg</path>
	<source>
		<database>Unknown</database>
	</source>
	<size>
		<width>300</width>
		<height>300</height>
		<depth>3</depth>
	</size>
	<segmented>0</segmented>
	<object>
		<name>消防栓</name>
		<pose>Unspecified</pose>
		<truncated>0</truncated>
		<difficult>0</difficult>
		<bndbox>
			<xmin>14</xmin>
			<ymin>28</ymin>
			<xmax>66</xmax>
			<ymax>95</ymax>
		</bndbox>
	</object>
	<object>
		<name>消防栓</name>
		<pose>Unspecified</pose>
		<truncated>0</truncated>
		<difficult>0</difficult>
		<bndbox>
			<xmin>134</xmin>
			<ymin>38</ymin>
			<xmax>171</xmax>
			<ymax>84</ymax>
		</bndbox>
	</object>
	<object>
		<name>消防栓</name>
		<pose>Unspecified</pose>
		<truncated>1</truncated>
		<difficult>0</difficult>
		<bndbox>
			<xmin>226</xmin>
			<ymin>1</ymin>
			<xmax>278</xmax>
			<ymax>73</ymax>
		</bndbox>
	</object>
	<object>
		<name>汽車</name>
		<pose>Unspecified</pose>
		<truncated>0</truncated>
		<difficult>0</difficult>
		<bndbox>
			<xmin>141</xmin>
			<ymin>147</ymin>
			<xmax>162</xmax>
			<ymax>167</ymax>
		</bndbox>
	</object>
	<object>
		<name>汽車</name>
		<pose>Unspecified</pose>
		<truncated>0</truncated>
		<difficult>0</difficult>
		<bndbox>
			<xmin>110</xmin>
			<ymin>140</ymin>
			<xmax>136</xmax>
			<ymax>153</ymax>
		</bndbox>
	</object>
	<object>
		<name>汽車</name>
		<pose>Unspecified</pose>
		<truncated>1</truncated>
		<difficult>0</difficult>
		<bndbox>
			<xmin>217</xmin>
			<ymin>99</ymin>
			<xmax>300</xmax>
			<ymax>189</ymax>
		</bndbox>
	</object>
	<object>
		<name>紅綠燈</name>
		<pose>Unspecified</pose>
		<truncated>0</truncated>
		<difficult>0</difficult>
		<bndbox>
			<xmin>257</xmin>
			<ymin>208</ymin>
			<xmax>288</xmax>
			<ymax>253</ymax>
		</bndbox>
	</object>
	<object>
		<name>紅綠燈</name>
		<pose>Unspecified</pose>
		<truncated>0</truncated>
		<difficult>0</difficult>
		<bndbox>
			<xmin>120</xmin>
			<ymin>214</ymin>
			<xmax>141</xmax>
			<ymax>253</ymax>
		</bndbox>
	</object>
	<object>
		<name>紅綠燈</name>
		<pose>Unspecified</pose>
		<truncated>0</truncated>
		<difficult>0</difficult>
		<bndbox>
			<xmin>176</xmin>
			<ymin>225</ymin>
			<xmax>193</xmax>
			<ymax>249</ymax>
		</bndbox>
	</object>
	<object>
		<name>汽車</name>
		<pose>Unspecified</pose>
		<truncated>0</truncated>
		<difficult>0</difficult>
		<bndbox>
			<xmin>30</xmin>
			<ymin>252</ymin>
			<xmax>47</xmax>
			<ymax>264</ymax>
		</bndbox>
	</object>
</annotation>
